redfish_use_case_checkers/__init__.py
redfish_use_case_checkers/account_management.py
redfish_use_case_checkers/boot_override.py
redfish_use_case_checkers/console_scripts.py
redfish_use_case_checkers/logger.py
redfish_use_case_checkers/manager_ethernet_interfaces.py
redfish_use_case_checkers/power_control.py
redfish_use_case_checkers/query_parameters.py
redfish_use_case_checkers/redfish_logo.py
redfish_use_case_checkers/report.py
redfish_use_case_checkers/system_under_test.py
redfish_use_case_checkers-2.0.7.dist-info/licenses/AUTHORS.md
redfish_use_case_checkers-2.0.7.dist-info/licenses/LICENSE.md
redfish_use_case_checkers-2.0.7.dist-info/METADATA
redfish_use_case_checkers-2.0.7.dist-info/WHEEL
redfish_use_case_checkers-2.0.7.dist-info/entry_points.txt
redfish_use_case_checkers-2.0.7.dist-info/top_level.txt
redfish_use_case_checkers-2.0.7.dist-info/RECORD
