Metadata-Version: 2.4
Name: redfish_use_case_checkers
Version: 2.0.7
Summary: Redfish Use Case Checkers
Home-page: https://github.com/DMTF/Redfish-Use-Case-Checkers
Author: DMTF, https://www.dmtf.org/standards/feedback
License: BSD 3-clause "New" or "Revised License"
Keywords: Redfish
Classifier: Development Status :: 5 - Production/Stable
Classifier: License :: OSI Approved :: BSD License
Classifier: Programming Language :: Python
Classifier: Topic :: Communications
License-File: LICENSE.md
License-File: AUTHORS.md
Requires-Dist: colorama
Requires-Dist: redfish>=3.0.0
Requires-Dist: redfish_utilities>=3.4.1
Dynamic: author
Dynamic: classifier
Dynamic: description
Dynamic: description-content-type
Dynamic: home-page
Dynamic: keywords
Dynamic: license
Dynamic: license-file
Dynamic: requires-dist
Dynamic: summary
